<?xml version="1.0" encoding="Windows-1252"?>
<assets>
    <assetTypeNumber>Sponsor Assigned</assetTypeNumber>
    <assetNumber>16219517</assetNumber>
    <reportingPeriodBeginningDate>11-01-2018</reportingPeriodBeginningDate>
    <reportingPeriodEndingDate>11-30-2018</reportingPeriodEndingDate>
    <originatorName>Ally Bank</originatorName>
    <originationDate>11/2013</originationDate>
    <originalLoanAmount>27797.08</originalLoanAmount>
    <originalLoanTerm>62</originalLoanTerm>
    <loanMaturityDate>12/2018</loanMaturityDate>
    <originalInterestRatePercentage>0.0544</originalInterestRatePercentage>
    <interestCalculationTypeCode>1</interestCalculationTypeCode>
    <originalInterestRateTypeCode>1</originalInterestRateTypeCode>
    <originalFirstPaymentDate>01/2014</originalFirstPaymentDate>
    <underwritingIndicator>true</underwritingIndicator>
    <gracePeriodNumber>2</gracePeriodNumber>
    <paymentTypeCode>2</paymentTypeCode>
    <subvented>0</subvented>
    <vehicleManufacturerName>FORD</vehicleManufacturerName>
    <vehicleModelName>Econoline Wagon</vehicleModelName>
    <vehicleNewUsedCode>2</vehicleNewUsedCode>
    <vehicleModelYear>2013</vehicleModelYear>
    <vehicleTypeCode>2</vehicleTypeCode>
    <vehicleValueAmount>21030.00</vehicleValueAmount>
    <vehicleValueSourceCode>3</vehicleValueSourceCode>
    <obligorCreditScoreType>Commercial Bureau</obligorCreditScoreType>
    <obligorCreditScore>577 </obligorCreditScore>
    <obligorIncomeVerificationLevelCode>1</obligorIncomeVerificationLevelCode>
    <obligorEmploymentVerificationCode>1</obligorEmploymentVerificationCode>
    <coObligorIndicator>false</coObligorIndicator>
    <paymentToIncomePercentage>0.0000</paymentToIncomePercentage>
    <obligorGeographicLocation>CA</obligorGeographicLocation>
    <assetAddedIndicator>false</assetAddedIndicator>
    <remainingTermToMaturityNumber>1</remainingTermToMaturityNumber>
    <servicingAdvanceMethodCode>1</servicingAdvanceMethodCode>
    <reportingPeriodBeginningLoanBalanceAmount>897.27</reportingPeriodBeginningLoanBalanceAmount>
    <nextReportingPeriodPaymentAmountDue>371.24</nextReportingPeriodPaymentAmountDue>
    <reportingPeriodInterestRatePercentage>0.0544</reportingPeriodInterestRatePercentage>
    <nextInterestRatePercentage>0.0544</nextInterestRatePercentage>
    <servicingFeePercentage>0.0100</servicingFeePercentage>
    <otherAssessedUncollectedServicerFeeAmount>220.15</otherAssessedUncollectedServicerFeeAmount>
    <scheduledInterestAmount>4.86</scheduledInterestAmount>
    <scheduledPrincipalAmount>526.43</scheduledPrincipalAmount>
    <otherPrincipalAdjustmentAmount>0.00</otherPrincipalAdjustmentAmount>
    <reportingPeriodActualEndBalanceAmount>370.25</reportingPeriodActualEndBalanceAmount>
    <reportingPeriodScheduledPaymentAmount>531.29</reportingPeriodScheduledPaymentAmount>
    <totalActualAmountPaid>531.29</totalActualAmountPaid>
    <actualInterestCollectedAmount>4.27</actualInterestCollectedAmount>
    <actualPrincipalCollectedAmount>527.02</actualPrincipalCollectedAmount>
    <actualOtherCollectedAmount>0.00</actualOtherCollectedAmount>
    <interestPaidThroughDate>11-19-2018</interestPaidThroughDate>
    <currentDelinquencyStatus>0</currentDelinquencyStatus>
    <primaryLoanServicerName>Ally Bank</primaryLoanServicerName>
    <assetSubjectDemandIndicator>false</assetSubjectDemandIndicator>
    <repossessedIndicator>false</repossessedIndicator>
    <repossessedProceedsAmount>0.00</repossessedProceedsAmount>
  </assets>