<?xml version="1.0" encoding="Windows-1252"?>
<assets>
    <assetTypeNumber>Sponsor Assigned</assetTypeNumber>
    <assetNumber>21552824</assetNumber>
    <reportingPeriodBeginningDate>11-01-2018</reportingPeriodBeginningDate>
    <reportingPeriodEndingDate>11-30-2018</reportingPeriodEndingDate>
    <originatorName>Ally Bank</originatorName>
    <originationDate>09/2017</originationDate>
    <originalLoanAmount>35954.16</originalLoanAmount>
    <originalLoanTerm>73</originalLoanTerm>
    <loanMaturityDate>09/2023</loanMaturityDate>
    <originalInterestRatePercentage>0.0550</originalInterestRatePercentage>
    <interestCalculationTypeCode>1</interestCalculationTypeCode>
    <originalInterestRateTypeCode>1</originalInterestRateTypeCode>
    <originalFirstPaymentDate>10/2017</originalFirstPaymentDate>
    <underwritingIndicator>true</underwritingIndicator>
    <gracePeriodNumber>1</gracePeriodNumber>
    <paymentTypeCode>2</paymentTypeCode>
    <subvented>2</subvented>
    <vehicleManufacturerName>CHEVROLET</vehicleManufacturerName>
    <vehicleModelName>Silverado                     </vehicleModelName>
    <vehicleNewUsedCode>1</vehicleNewUsedCode>
    <vehicleModelYear>2017</vehicleModelYear>
    <vehicleTypeCode>2</vehicleTypeCode>
    <vehicleValueAmount>47683.00</vehicleValueAmount>
    <vehicleValueSourceCode>1</vehicleValueSourceCode>
    <obligorCreditScoreType>Consumer Bureau</obligorCreditScoreType>
    <obligorCreditScore>702</obligorCreditScore>
    <obligorIncomeVerificationLevelCode>2</obligorIncomeVerificationLevelCode>
    <obligorEmploymentVerificationCode>2</obligorEmploymentVerificationCode>
    <coObligorIndicator>false</coObligorIndicator>
    <paymentToIncomePercentage>0.0587</paymentToIncomePercentage>
    <obligorGeographicLocation>AR</obligorGeographicLocation>
    <assetAddedIndicator>false</assetAddedIndicator>
    <remainingTermToMaturityNumber>58</remainingTermToMaturityNumber>
    <servicingAdvanceMethodCode>1</servicingAdvanceMethodCode>
    <reportingPeriodBeginningLoanBalanceAmount>30321.45</reportingPeriodBeginningLoanBalanceAmount>
    <nextReportingPeriodPaymentAmountDue>586.41</nextReportingPeriodPaymentAmountDue>
    <reportingPeriodInterestRatePercentage>0.0550</reportingPeriodInterestRatePercentage>
    <nextInterestRatePercentage>0.0550</nextInterestRatePercentage>
    <servicingFeePercentage>0.0100</servicingFeePercentage>
    <otherAssessedUncollectedServicerFeeAmount>1.00</otherAssessedUncollectedServicerFeeAmount>
    <scheduledInterestAmount>141.56</scheduledInterestAmount>
    <scheduledPrincipalAmount>445.85</scheduledPrincipalAmount>
    <otherPrincipalAdjustmentAmount>-4.64</otherPrincipalAdjustmentAmount>
    <reportingPeriodActualEndBalanceAmount>29880.24</reportingPeriodActualEndBalanceAmount>
    <reportingPeriodScheduledPaymentAmount>587.41</reportingPeriodScheduledPaymentAmount>
    <totalActualAmountPaid>587.41</totalActualAmountPaid>
    <actualInterestCollectedAmount>146.20</actualInterestCollectedAmount>
    <actualPrincipalCollectedAmount>441.21</actualPrincipalCollectedAmount>
    <actualOtherCollectedAmount>0.00</actualOtherCollectedAmount>
    <interestPaidThroughDate>11-20-2018</interestPaidThroughDate>
    <currentDelinquencyStatus>0</currentDelinquencyStatus>
    <primaryLoanServicerName>Ally Bank</primaryLoanServicerName>
    <assetSubjectDemandIndicator>false</assetSubjectDemandIndicator>
    <repossessedIndicator>false</repossessedIndicator>
    <repossessedProceedsAmount>0.00</repossessedProceedsAmount>
  </assets>