<?xml version="1.0" encoding="Windows-1252"?>
<assets>
    <assetTypeNumber>Sponsor Assigned</assetTypeNumber>
    <assetNumber>21578327</assetNumber>
    <reportingPeriodBeginningDate>11-01-2018</reportingPeriodBeginningDate>
    <reportingPeriodEndingDate>11-30-2018</reportingPeriodEndingDate>
    <originatorName>Ally Bank</originatorName>
    <originationDate>09/2017</originationDate>
    <originalLoanAmount>22895.89</originalLoanAmount>
    <originalLoanTerm>76</originalLoanTerm>
    <loanMaturityDate>12/2023</loanMaturityDate>
    <originalInterestRatePercentage>0.1260</originalInterestRatePercentage>
    <interestCalculationTypeCode>1</interestCalculationTypeCode>
    <originalInterestRateTypeCode>1</originalInterestRateTypeCode>
    <originalFirstPaymentDate>10/2017</originalFirstPaymentDate>
    <underwritingIndicator>true</underwritingIndicator>
    <gracePeriodNumber>1</gracePeriodNumber>
    <paymentTypeCode>2</paymentTypeCode>
    <subvented>2</subvented>
    <vehicleManufacturerName>KIA</vehicleManufacturerName>
    <vehicleModelName>Forte                         </vehicleModelName>
    <vehicleNewUsedCode>1</vehicleNewUsedCode>
    <vehicleModelYear>2017</vehicleModelYear>
    <vehicleTypeCode>1</vehicleTypeCode>
    <vehicleValueAmount>18227.00</vehicleValueAmount>
    <vehicleValueSourceCode>1</vehicleValueSourceCode>
    <obligorCreditScoreType>Consumer Bureau</obligorCreditScoreType>
    <obligorCreditScore>729</obligorCreditScore>
    <obligorIncomeVerificationLevelCode>3</obligorIncomeVerificationLevelCode>
    <obligorEmploymentVerificationCode>3</obligorEmploymentVerificationCode>
    <coObligorIndicator>false</coObligorIndicator>
    <paymentToIncomePercentage>0.2094</paymentToIncomePercentage>
    <obligorGeographicLocation>TX</obligorGeographicLocation>
    <assetAddedIndicator>false</assetAddedIndicator>
    <remainingTermToMaturityNumber>61</remainingTermToMaturityNumber>
    <servicingAdvanceMethodCode>1</servicingAdvanceMethodCode>
    <reportingPeriodBeginningLoanBalanceAmount>20510.21</reportingPeriodBeginningLoanBalanceAmount>
    <nextReportingPeriodPaymentAmountDue>889.82</nextReportingPeriodPaymentAmountDue>
    <reportingPeriodInterestRatePercentage>0.1260</reportingPeriodInterestRatePercentage>
    <nextInterestRatePercentage>0.1260</nextInterestRatePercentage>
    <servicingFeePercentage>0.0100</servicingFeePercentage>
    <otherAssessedUncollectedServicerFeeAmount>22.24</otherAssessedUncollectedServicerFeeAmount>
    <scheduledInterestAmount>216.02</scheduledInterestAmount>
    <scheduledPrincipalAmount>228.89</scheduledPrincipalAmount>
    <otherPrincipalAdjustmentAmount>-45.94</otherPrincipalAdjustmentAmount>
    <reportingPeriodActualEndBalanceAmount>20327.26</reportingPeriodActualEndBalanceAmount>
    <reportingPeriodScheduledPaymentAmount>444.91</reportingPeriodScheduledPaymentAmount>
    <totalActualAmountPaid>444.91</totalActualAmountPaid>
    <actualInterestCollectedAmount>261.96</actualInterestCollectedAmount>
    <actualPrincipalCollectedAmount>182.95</actualPrincipalCollectedAmount>
    <actualOtherCollectedAmount>0.00</actualOtherCollectedAmount>
    <interestPaidThroughDate>11-16-2018</interestPaidThroughDate>
    <currentDelinquencyStatus>0</currentDelinquencyStatus>
    <primaryLoanServicerName>Ally Bank</primaryLoanServicerName>
    <assetSubjectDemandIndicator>false</assetSubjectDemandIndicator>
    <repossessedIndicator>false</repossessedIndicator>
    <repossessedProceedsAmount>0.00</repossessedProceedsAmount>
  </assets>