<?xml version="1.0" encoding="Windows-1252"?>
<assets>
    <assetTypeNumber>Sponsor Assigned</assetTypeNumber>
    <assetNumber>21750149</assetNumber>
    <reportingPeriodBeginningDate>11-01-2018</reportingPeriodBeginningDate>
    <reportingPeriodEndingDate>11-30-2018</reportingPeriodEndingDate>
    <originatorName>Ally Bank</originatorName>
    <originationDate>11/2017</originationDate>
    <originalLoanAmount>19706.32</originalLoanAmount>
    <originalLoanTerm>73</originalLoanTerm>
    <loanMaturityDate>11/2023</loanMaturityDate>
    <originalInterestRatePercentage>0.0430</originalInterestRatePercentage>
    <interestCalculationTypeCode>1</interestCalculationTypeCode>
    <originalInterestRateTypeCode>1</originalInterestRateTypeCode>
    <originalFirstPaymentDate>12/2017</originalFirstPaymentDate>
    <underwritingIndicator>true</underwritingIndicator>
    <gracePeriodNumber>1</gracePeriodNumber>
    <paymentTypeCode>2</paymentTypeCode>
    <subvented>2</subvented>
    <vehicleManufacturerName>GMC</vehicleManufacturerName>
    <vehicleModelName>Canyon                        </vehicleModelName>
    <vehicleNewUsedCode>1</vehicleNewUsedCode>
    <vehicleModelYear>2017</vehicleModelYear>
    <vehicleTypeCode>2</vehicleTypeCode>
    <vehicleValueAmount>32823.00</vehicleValueAmount>
    <vehicleValueSourceCode>1</vehicleValueSourceCode>
    <obligorCreditScoreType>Commercial Bureau</obligorCreditScoreType>
    <obligorCreditScore>512 </obligorCreditScore>
    <obligorIncomeVerificationLevelCode>1</obligorIncomeVerificationLevelCode>
    <obligorEmploymentVerificationCode>1</obligorEmploymentVerificationCode>
    <coObligorIndicator>false</coObligorIndicator>
    <paymentToIncomePercentage>0.0000</paymentToIncomePercentage>
    <obligorGeographicLocation>CA</obligorGeographicLocation>
    <assetAddedIndicator>false</assetAddedIndicator>
    <remainingTermToMaturityNumber>60</remainingTermToMaturityNumber>
    <servicingAdvanceMethodCode>1</servicingAdvanceMethodCode>
    <reportingPeriodBeginningLoanBalanceAmount>13185.27</reportingPeriodBeginningLoanBalanceAmount>
    <nextReportingPeriodPaymentAmountDue>0.00</nextReportingPeriodPaymentAmountDue>
    <reportingPeriodInterestRatePercentage>0.0430</reportingPeriodInterestRatePercentage>
    <nextInterestRatePercentage>0.0430</nextInterestRatePercentage>
    <servicingFeePercentage>0.0100</servicingFeePercentage>
    <otherAssessedUncollectedServicerFeeAmount>0.00</otherAssessedUncollectedServicerFeeAmount>
    <scheduledInterestAmount>62.13</scheduledInterestAmount>
    <scheduledPrincipalAmount>248.88</scheduledPrincipalAmount>
    <otherPrincipalAdjustmentAmount>0.00</otherPrincipalAdjustmentAmount>
    <reportingPeriodActualEndBalanceAmount>12349.11</reportingPeriodActualEndBalanceAmount>
    <reportingPeriodScheduledPaymentAmount>311.01</reportingPeriodScheduledPaymentAmount>
    <totalActualAmountPaid>900.00</totalActualAmountPaid>
    <actualInterestCollectedAmount>63.84</actualInterestCollectedAmount>
    <actualPrincipalCollectedAmount>836.16</actualPrincipalCollectedAmount>
    <actualOtherCollectedAmount>0.00</actualOtherCollectedAmount>
    <interestPaidThroughDate>11-30-2018</interestPaidThroughDate>
    <currentDelinquencyStatus>0</currentDelinquencyStatus>
    <primaryLoanServicerName>Ally Bank</primaryLoanServicerName>
    <assetSubjectDemandIndicator>false</assetSubjectDemandIndicator>
    <repossessedIndicator>false</repossessedIndicator>
    <repossessedProceedsAmount>0.00</repossessedProceedsAmount>
  </assets>