<?xml version="1.0" encoding="Windows-1252"?>
<assets>
    <assetTypeNumber>Sponsor Assigned</assetTypeNumber>
    <assetNumber>21914289</assetNumber>
    <reportingPeriodBeginningDate>11-01-2018</reportingPeriodBeginningDate>
    <reportingPeriodEndingDate>11-30-2018</reportingPeriodEndingDate>
    <originatorName>Ally Bank</originatorName>
    <originationDate>12/2017</originationDate>
    <originalLoanAmount>32086.76</originalLoanAmount>
    <originalLoanTerm>73</originalLoanTerm>
    <loanMaturityDate>12/2023</loanMaturityDate>
    <originalInterestRatePercentage>0.0314</originalInterestRatePercentage>
    <interestCalculationTypeCode>1</interestCalculationTypeCode>
    <originalInterestRateTypeCode>1</originalInterestRateTypeCode>
    <originalFirstPaymentDate>01/2018</originalFirstPaymentDate>
    <underwritingIndicator>true</underwritingIndicator>
    <gracePeriodNumber>1</gracePeriodNumber>
    <paymentTypeCode>2</paymentTypeCode>
    <subvented>2</subvented>
    <vehicleManufacturerName>GMC</vehicleManufacturerName>
    <vehicleModelName>Acadia                        </vehicleModelName>
    <vehicleNewUsedCode>1</vehicleNewUsedCode>
    <vehicleModelYear>2017</vehicleModelYear>
    <vehicleTypeCode>3</vehicleTypeCode>
    <vehicleValueAmount>35597.00</vehicleValueAmount>
    <vehicleValueSourceCode>1</vehicleValueSourceCode>
    <obligorCreditScoreType>Consumer Bureau</obligorCreditScoreType>
    <obligorCreditScore>776</obligorCreditScore>
    <obligorIncomeVerificationLevelCode>2</obligorIncomeVerificationLevelCode>
    <obligorEmploymentVerificationCode>2</obligorEmploymentVerificationCode>
    <coObligorIndicator>false</coObligorIndicator>
    <paymentToIncomePercentage>0.0112</paymentToIncomePercentage>
    <obligorGeographicLocation>TX</obligorGeographicLocation>
    <assetAddedIndicator>false</assetAddedIndicator>
    <remainingTermToMaturityNumber>61</remainingTermToMaturityNumber>
    <servicingAdvanceMethodCode>1</servicingAdvanceMethodCode>
    <reportingPeriodBeginningLoanBalanceAmount>27871.03</reportingPeriodBeginningLoanBalanceAmount>
    <nextReportingPeriodPaymentAmountDue>374.84</nextReportingPeriodPaymentAmountDue>
    <reportingPeriodInterestRatePercentage>0.0314</reportingPeriodInterestRatePercentage>
    <nextInterestRatePercentage>0.0314</nextInterestRatePercentage>
    <servicingFeePercentage>0.0100</servicingFeePercentage>
    <otherAssessedUncollectedServicerFeeAmount>0.00</otherAssessedUncollectedServicerFeeAmount>
    <scheduledInterestAmount>74.62</scheduledInterestAmount>
    <scheduledPrincipalAmount>414.95</scheduledPrincipalAmount>
    <otherPrincipalAdjustmentAmount>0.00</otherPrincipalAdjustmentAmount>
    <reportingPeriodActualEndBalanceAmount>27447.74</reportingPeriodActualEndBalanceAmount>
    <reportingPeriodScheduledPaymentAmount>489.57</reportingPeriodScheduledPaymentAmount>
    <totalActualAmountPaid>500.00</totalActualAmountPaid>
    <actualInterestCollectedAmount>76.71</actualInterestCollectedAmount>
    <actualPrincipalCollectedAmount>423.29</actualPrincipalCollectedAmount>
    <actualOtherCollectedAmount>0.00</actualOtherCollectedAmount>
    <interestPaidThroughDate>11-13-2018</interestPaidThroughDate>
    <currentDelinquencyStatus>0</currentDelinquencyStatus>
    <primaryLoanServicerName>Ally Bank</primaryLoanServicerName>
    <assetSubjectDemandIndicator>false</assetSubjectDemandIndicator>
    <repossessedIndicator>false</repossessedIndicator>
    <repossessedProceedsAmount>0.00</repossessedProceedsAmount>
  </assets>