<?xml version="1.0" encoding="Windows-1252"?>
<assets>
    <assetTypeNumber>Sponsor Assigned</assetTypeNumber>
    <assetNumber>22310000</assetNumber>
    <reportingPeriodBeginningDate>11-01-2018</reportingPeriodBeginningDate>
    <reportingPeriodEndingDate>11-30-2018</reportingPeriodEndingDate>
    <originatorName>Ally Bank</originatorName>
    <originationDate>03/2018</originationDate>
    <originalLoanAmount>44953.54</originalLoanAmount>
    <originalLoanTerm>74</originalLoanTerm>
    <loanMaturityDate>04/2024</loanMaturityDate>
    <originalInterestRatePercentage>0.0684</originalInterestRatePercentage>
    <interestCalculationTypeCode>1</interestCalculationTypeCode>
    <originalInterestRateTypeCode>1</originalInterestRateTypeCode>
    <originalFirstPaymentDate>05/2018</originalFirstPaymentDate>
    <underwritingIndicator>true</underwritingIndicator>
    <gracePeriodNumber>2</gracePeriodNumber>
    <paymentTypeCode>2</paymentTypeCode>
    <subvented>0</subvented>
    <vehicleManufacturerName>VOLVO</vehicleManufacturerName>
    <vehicleModelName>XC40</vehicleModelName>
    <vehicleNewUsedCode>1</vehicleNewUsedCode>
    <vehicleModelYear>2019</vehicleModelYear>
    <vehicleTypeCode>3</vehicleTypeCode>
    <vehicleValueAmount>43982.00</vehicleValueAmount>
    <vehicleValueSourceCode>1</vehicleValueSourceCode>
    <obligorCreditScoreType>Consumer Bureau</obligorCreditScoreType>
    <obligorCreditScore>686</obligorCreditScore>
    <obligorIncomeVerificationLevelCode>2</obligorIncomeVerificationLevelCode>
    <obligorEmploymentVerificationCode>2</obligorEmploymentVerificationCode>
    <coObligorIndicator>false</coObligorIndicator>
    <paymentToIncomePercentage>0.1177</paymentToIncomePercentage>
    <obligorGeographicLocation>NC</obligorGeographicLocation>
    <assetAddedIndicator>false</assetAddedIndicator>
    <remainingTermToMaturityNumber>65</remainingTermToMaturityNumber>
    <servicingAdvanceMethodCode>1</servicingAdvanceMethodCode>
    <reportingPeriodBeginningLoanBalanceAmount>41991.83</reportingPeriodBeginningLoanBalanceAmount>
    <nextReportingPeriodPaymentAmountDue>765.11</nextReportingPeriodPaymentAmountDue>
    <reportingPeriodInterestRatePercentage>0.0684</reportingPeriodInterestRatePercentage>
    <nextInterestRatePercentage>0.0684</nextInterestRatePercentage>
    <servicingFeePercentage>0.0100</servicingFeePercentage>
    <otherAssessedUncollectedServicerFeeAmount>0.00</otherAssessedUncollectedServicerFeeAmount>
    <scheduledInterestAmount>243.90</scheduledInterestAmount>
    <scheduledPrincipalAmount>521.21</scheduledPrincipalAmount>
    <otherPrincipalAdjustmentAmount>-0.03</otherPrincipalAdjustmentAmount>
    <reportingPeriodActualEndBalanceAmount>41470.65</reportingPeriodActualEndBalanceAmount>
    <reportingPeriodScheduledPaymentAmount>765.11</reportingPeriodScheduledPaymentAmount>
    <totalActualAmountPaid>765.11</totalActualAmountPaid>
    <actualInterestCollectedAmount>243.93</actualInterestCollectedAmount>
    <actualPrincipalCollectedAmount>521.18</actualPrincipalCollectedAmount>
    <actualOtherCollectedAmount>0.00</actualOtherCollectedAmount>
    <interestPaidThroughDate>11-08-2018</interestPaidThroughDate>
    <currentDelinquencyStatus>0</currentDelinquencyStatus>
    <primaryLoanServicerName>Ally Bank</primaryLoanServicerName>
    <assetSubjectDemandIndicator>false</assetSubjectDemandIndicator>
    <repossessedIndicator>false</repossessedIndicator>
    <repossessedProceedsAmount>0.00</repossessedProceedsAmount>
  </assets>