<?xml version="1.0" encoding="Windows-1252"?>
<assets>
    <assetTypeNumber>Sponsor Assigned</assetTypeNumber>
    <assetNumber>20788786</assetNumber>
    <reportingPeriodBeginningDate>11-01-2018</reportingPeriodBeginningDate>
    <reportingPeriodEndingDate>11-30-2018</reportingPeriodEndingDate>
    <originatorName>Ally Bank</originatorName>
    <originationDate>02/2017</originationDate>
    <originalLoanAmount>27922.73</originalLoanAmount>
    <originalLoanTerm>76</originalLoanTerm>
    <loanMaturityDate>05/2023</loanMaturityDate>
    <originalInterestRatePercentage>0.1210</originalInterestRatePercentage>
    <interestCalculationTypeCode>1</interestCalculationTypeCode>
    <originalInterestRateTypeCode>1</originalInterestRateTypeCode>
    <originalFirstPaymentDate>03/2017</originalFirstPaymentDate>
    <underwritingIndicator>true</underwritingIndicator>
    <gracePeriodNumber>1</gracePeriodNumber>
    <paymentTypeCode>2</paymentTypeCode>
    <subvented>0</subvented>
    <vehicleManufacturerName>CHEVROLET</vehicleManufacturerName>
    <vehicleModelName>Trax                          </vehicleModelName>
    <vehicleNewUsedCode>1</vehicleNewUsedCode>
    <vehicleModelYear>2017</vehicleModelYear>
    <vehicleTypeCode>3</vehicleTypeCode>
    <vehicleValueAmount>21370.00</vehicleValueAmount>
    <vehicleValueSourceCode>1</vehicleValueSourceCode>
    <obligorCreditScoreType>Consumer Bureau</obligorCreditScoreType>
    <obligorCreditScore>678</obligorCreditScore>
    <obligorIncomeVerificationLevelCode>2</obligorIncomeVerificationLevelCode>
    <obligorEmploymentVerificationCode>2</obligorEmploymentVerificationCode>
    <coObligorIndicator>false</coObligorIndicator>
    <paymentToIncomePercentage>0.1167</paymentToIncomePercentage>
    <obligorGeographicLocation>MI</obligorGeographicLocation>
    <assetAddedIndicator>false</assetAddedIndicator>
    <remainingTermToMaturityNumber>54</remainingTermToMaturityNumber>
    <servicingAdvanceMethodCode>1</servicingAdvanceMethodCode>
    <reportingPeriodBeginningLoanBalanceAmount>22473.79</reportingPeriodBeginningLoanBalanceAmount>
    <nextReportingPeriodPaymentAmountDue>534.74</nextReportingPeriodPaymentAmountDue>
    <reportingPeriodInterestRatePercentage>0.1210</reportingPeriodInterestRatePercentage>
    <nextInterestRatePercentage>0.1210</nextInterestRatePercentage>
    <servicingFeePercentage>0.0100</servicingFeePercentage>
    <otherAssessedUncollectedServicerFeeAmount>0.00</otherAssessedUncollectedServicerFeeAmount>
    <scheduledInterestAmount>230.85</scheduledInterestAmount>
    <scheduledPrincipalAmount>303.89</scheduledPrincipalAmount>
    <otherPrincipalAdjustmentAmount>-0.10</otherPrincipalAdjustmentAmount>
    <reportingPeriodActualEndBalanceAmount>22170.00</reportingPeriodActualEndBalanceAmount>
    <reportingPeriodScheduledPaymentAmount>534.74</reportingPeriodScheduledPaymentAmount>
    <totalActualAmountPaid>534.74</totalActualAmountPaid>
    <actualInterestCollectedAmount>230.95</actualInterestCollectedAmount>
    <actualPrincipalCollectedAmount>303.79</actualPrincipalCollectedAmount>
    <actualOtherCollectedAmount>0.00</actualOtherCollectedAmount>
    <interestPaidThroughDate>11-26-2018</interestPaidThroughDate>
    <currentDelinquencyStatus>0</currentDelinquencyStatus>
    <primaryLoanServicerName>Ally Bank</primaryLoanServicerName>
    <assetSubjectDemandIndicator>false</assetSubjectDemandIndicator>
    <repossessedIndicator>false</repossessedIndicator>
    <repossessedProceedsAmount>0.00</repossessedProceedsAmount>
  </assets>