<?xml version="1.0" encoding="Windows-1252"?>
<assets>
    <assetTypeNumber>Sponsor Assigned</assetTypeNumber>
    <assetNumber>18871923</assetNumber>
    <reportingPeriodBeginningDate>11-01-2018</reportingPeriodBeginningDate>
    <reportingPeriodEndingDate>11-30-2018</reportingPeriodEndingDate>
    <originatorName>Ally Bank</originatorName>
    <originationDate>09/2015</originationDate>
    <originalLoanAmount>19768.75</originalLoanAmount>
    <originalLoanTerm>64</originalLoanTerm>
    <loanMaturityDate>12/2020</loanMaturityDate>
    <originalInterestRatePercentage>0.0554</originalInterestRatePercentage>
    <interestCalculationTypeCode>1</interestCalculationTypeCode>
    <originalInterestRateTypeCode>1</originalInterestRateTypeCode>
    <originalFirstPaymentDate>10/2015</originalFirstPaymentDate>
    <underwritingIndicator>true</underwritingIndicator>
    <gracePeriodNumber>1</gracePeriodNumber>
    <paymentTypeCode>2</paymentTypeCode>
    <subvented>0</subvented>
    <vehicleManufacturerName>KIA</vehicleManufacturerName>
    <vehicleModelName>Sportage                      </vehicleModelName>
    <vehicleNewUsedCode>2</vehicleNewUsedCode>
    <vehicleModelYear>2011</vehicleModelYear>
    <vehicleTypeCode>3</vehicleTypeCode>
    <vehicleValueAmount>15300.00</vehicleValueAmount>
    <vehicleValueSourceCode>98</vehicleValueSourceCode>
    <obligorCreditScoreType>Consumer Bureau</obligorCreditScoreType>
    <obligorCreditScore>716</obligorCreditScore>
    <obligorIncomeVerificationLevelCode>2</obligorIncomeVerificationLevelCode>
    <obligorEmploymentVerificationCode>2</obligorEmploymentVerificationCode>
    <coObligorIndicator>true</coObligorIndicator>
    <paymentToIncomePercentage>0.0303</paymentToIncomePercentage>
    <obligorGeographicLocation>GA</obligorGeographicLocation>
    <assetAddedIndicator>false</assetAddedIndicator>
    <remainingTermToMaturityNumber>25</remainingTermToMaturityNumber>
    <servicingAdvanceMethodCode>1</servicingAdvanceMethodCode>
    <reportingPeriodBeginningLoanBalanceAmount>8877.02</reportingPeriodBeginningLoanBalanceAmount>
    <nextReportingPeriodPaymentAmountDue>363.17</nextReportingPeriodPaymentAmountDue>
    <reportingPeriodInterestRatePercentage>0.0554</reportingPeriodInterestRatePercentage>
    <nextInterestRatePercentage>0.0554</nextInterestRatePercentage>
    <servicingFeePercentage>0.0100</servicingFeePercentage>
    <otherAssessedUncollectedServicerFeeAmount>0.00</otherAssessedUncollectedServicerFeeAmount>
    <scheduledInterestAmount>41.77</scheduledInterestAmount>
    <scheduledPrincipalAmount>321.40</scheduledPrincipalAmount>
    <otherPrincipalAdjustmentAmount>0.00</otherPrincipalAdjustmentAmount>
    <reportingPeriodActualEndBalanceAmount>8555.61</reportingPeriodActualEndBalanceAmount>
    <reportingPeriodScheduledPaymentAmount>363.17</reportingPeriodScheduledPaymentAmount>
    <totalActualAmountPaid>363.17</totalActualAmountPaid>
    <actualInterestCollectedAmount>41.76</actualInterestCollectedAmount>
    <actualPrincipalCollectedAmount>321.41</actualPrincipalCollectedAmount>
    <actualOtherCollectedAmount>0.00</actualOtherCollectedAmount>
    <interestPaidThroughDate>11-22-2018</interestPaidThroughDate>
    <currentDelinquencyStatus>0</currentDelinquencyStatus>
    <primaryLoanServicerName>Ally Bank</primaryLoanServicerName>
    <assetSubjectDemandIndicator>false</assetSubjectDemandIndicator>
    <repossessedIndicator>false</repossessedIndicator>
    <repossessedProceedsAmount>0.00</repossessedProceedsAmount>
  </assets>