<?xml version="1.0" encoding="Windows-1252"?>
<assets>
    <assetTypeNumber>Sponsor Assigned</assetTypeNumber>
    <assetNumber>19127426</assetNumber>
    <reportingPeriodBeginningDate>11-01-2018</reportingPeriodBeginningDate>
    <reportingPeriodEndingDate>11-30-2018</reportingPeriodEndingDate>
    <originatorName>Ally Bank</originatorName>
    <originationDate>10/2015</originationDate>
    <originalLoanAmount>30343.95</originalLoanAmount>
    <originalLoanTerm>77</originalLoanTerm>
    <loanMaturityDate>02/2022</loanMaturityDate>
    <originalInterestRatePercentage>0.0499</originalInterestRatePercentage>
    <interestCalculationTypeCode>1</interestCalculationTypeCode>
    <originalInterestRateTypeCode>1</originalInterestRateTypeCode>
    <originalFirstPaymentDate>12/2015</originalFirstPaymentDate>
    <underwritingIndicator>true</underwritingIndicator>
    <gracePeriodNumber>2</gracePeriodNumber>
    <paymentTypeCode>2</paymentTypeCode>
    <subvented>2</subvented>
    <vehicleManufacturerName>HYUNDAI</vehicleManufacturerName>
    <vehicleModelName>Tucson                        </vehicleModelName>
    <vehicleNewUsedCode>1</vehicleNewUsedCode>
    <vehicleModelYear>2016</vehicleModelYear>
    <vehicleTypeCode>3</vehicleTypeCode>
    <vehicleValueAmount>23919.00</vehicleValueAmount>
    <vehicleValueSourceCode>1</vehicleValueSourceCode>
    <obligorCreditScoreType>Consumer Bureau</obligorCreditScoreType>
    <obligorCreditScore>666</obligorCreditScore>
    <obligorIncomeVerificationLevelCode>2</obligorIncomeVerificationLevelCode>
    <obligorEmploymentVerificationCode>2</obligorEmploymentVerificationCode>
    <coObligorIndicator>true</coObligorIndicator>
    <paymentToIncomePercentage>0.0566</paymentToIncomePercentage>
    <obligorGeographicLocation>OK</obligorGeographicLocation>
    <assetAddedIndicator>false</assetAddedIndicator>
    <remainingTermToMaturityNumber>39</remainingTermToMaturityNumber>
    <servicingAdvanceMethodCode>1</servicingAdvanceMethodCode>
    <reportingPeriodBeginningLoanBalanceAmount>17248.56</reportingPeriodBeginningLoanBalanceAmount>
    <nextReportingPeriodPaymentAmountDue>336.56</nextReportingPeriodPaymentAmountDue>
    <reportingPeriodInterestRatePercentage>0.0499</reportingPeriodInterestRatePercentage>
    <nextInterestRatePercentage>0.0499</nextInterestRatePercentage>
    <servicingFeePercentage>0.0100</servicingFeePercentage>
    <otherAssessedUncollectedServicerFeeAmount>0.00</otherAssessedUncollectedServicerFeeAmount>
    <scheduledInterestAmount>73.68</scheduledInterestAmount>
    <scheduledPrincipalAmount>399.08</scheduledPrincipalAmount>
    <otherPrincipalAdjustmentAmount>0.00</otherPrincipalAdjustmentAmount>
    <reportingPeriodActualEndBalanceAmount>16824.01</reportingPeriodActualEndBalanceAmount>
    <reportingPeriodScheduledPaymentAmount>472.76</reportingPeriodScheduledPaymentAmount>
    <totalActualAmountPaid>500.00</totalActualAmountPaid>
    <actualInterestCollectedAmount>75.45</actualInterestCollectedAmount>
    <actualPrincipalCollectedAmount>424.55</actualPrincipalCollectedAmount>
    <actualOtherCollectedAmount>0.00</actualOtherCollectedAmount>
    <interestPaidThroughDate>11-06-2018</interestPaidThroughDate>
    <currentDelinquencyStatus>0</currentDelinquencyStatus>
    <primaryLoanServicerName>Ally Bank</primaryLoanServicerName>
    <assetSubjectDemandIndicator>false</assetSubjectDemandIndicator>
    <repossessedIndicator>false</repossessedIndicator>
    <repossessedProceedsAmount>0.00</repossessedProceedsAmount>
  </assets>