<?xml version="1.0" encoding="Windows-1252"?>
<assets>
    <assetTypeNumber>Sponsor Assigned</assetTypeNumber>
    <assetNumber>20270229</assetNumber>
    <reportingPeriodBeginningDate>11-01-2018</reportingPeriodBeginningDate>
    <reportingPeriodEndingDate>11-30-2018</reportingPeriodEndingDate>
    <originatorName>Ally Bank</originatorName>
    <originationDate>09/2016</originationDate>
    <originalLoanAmount>25782.45</originalLoanAmount>
    <originalLoanTerm>76</originalLoanTerm>
    <loanMaturityDate>01/2023</loanMaturityDate>
    <originalInterestRatePercentage>0.1000</originalInterestRatePercentage>
    <interestCalculationTypeCode>1</interestCalculationTypeCode>
    <originalInterestRateTypeCode>1</originalInterestRateTypeCode>
    <originalFirstPaymentDate>10/2016</originalFirstPaymentDate>
    <underwritingIndicator>true</underwritingIndicator>
    <gracePeriodNumber>1</gracePeriodNumber>
    <paymentTypeCode>2</paymentTypeCode>
    <subvented>2</subvented>
    <vehicleManufacturerName>DODGE</vehicleManufacturerName>
    <vehicleModelName>Charger                       </vehicleModelName>
    <vehicleNewUsedCode>1</vehicleNewUsedCode>
    <vehicleModelYear>2016</vehicleModelYear>
    <vehicleTypeCode>1</vehicleTypeCode>
    <vehicleValueAmount>28572.00</vehicleValueAmount>
    <vehicleValueSourceCode>1</vehicleValueSourceCode>
    <obligorCreditScoreType>Consumer Bureau</obligorCreditScoreType>
    <obligorCreditScore>707</obligorCreditScore>
    <obligorIncomeVerificationLevelCode>2</obligorIncomeVerificationLevelCode>
    <obligorEmploymentVerificationCode>2</obligorEmploymentVerificationCode>
    <coObligorIndicator>true</coObligorIndicator>
    <paymentToIncomePercentage>0.1900</paymentToIncomePercentage>
    <obligorGeographicLocation>TX</obligorGeographicLocation>
    <assetAddedIndicator>false</assetAddedIndicator>
    <remainingTermToMaturityNumber>50</remainingTermToMaturityNumber>
    <servicingAdvanceMethodCode>1</servicingAdvanceMethodCode>
    <reportingPeriodBeginningLoanBalanceAmount>18898.80</reportingPeriodBeginningLoanBalanceAmount>
    <nextReportingPeriodPaymentAmountDue>465.61</nextReportingPeriodPaymentAmountDue>
    <reportingPeriodInterestRatePercentage>0.1000</reportingPeriodInterestRatePercentage>
    <nextInterestRatePercentage>0.1000</nextInterestRatePercentage>
    <servicingFeePercentage>0.0100</servicingFeePercentage>
    <otherAssessedUncollectedServicerFeeAmount>0.00</otherAssessedUncollectedServicerFeeAmount>
    <scheduledInterestAmount>161.06</scheduledInterestAmount>
    <scheduledPrincipalAmount>304.55</scheduledPrincipalAmount>
    <otherPrincipalAdjustmentAmount>0.00</otherPrincipalAdjustmentAmount>
    <reportingPeriodActualEndBalanceAmount>18593.69</reportingPeriodActualEndBalanceAmount>
    <reportingPeriodScheduledPaymentAmount>465.61</reportingPeriodScheduledPaymentAmount>
    <totalActualAmountPaid>465.61</totalActualAmountPaid>
    <actualInterestCollectedAmount>160.50</actualInterestCollectedAmount>
    <actualPrincipalCollectedAmount>305.11</actualPrincipalCollectedAmount>
    <actualOtherCollectedAmount>0.00</actualOtherCollectedAmount>
    <interestPaidThroughDate>11-12-2018</interestPaidThroughDate>
    <currentDelinquencyStatus>0</currentDelinquencyStatus>
    <primaryLoanServicerName>Ally Bank</primaryLoanServicerName>
    <assetSubjectDemandIndicator>false</assetSubjectDemandIndicator>
    <repossessedIndicator>false</repossessedIndicator>
    <repossessedProceedsAmount>0.00</repossessedProceedsAmount>
  </assets>