<?xml version="1.0" encoding="Windows-1252"?>
<assets>
    <assetTypeNumber>Sponsor Assigned</assetTypeNumber>
    <assetNumber>17124190</assetNumber>
    <reportingPeriodBeginningDate>11-01-2018</reportingPeriodBeginningDate>
    <reportingPeriodEndingDate>11-30-2018</reportingPeriodEndingDate>
    <originatorName>Ally Bank</originatorName>
    <originationDate>07/2014</originationDate>
    <originalLoanAmount>27870.94</originalLoanAmount>
    <originalLoanTerm>73</originalLoanTerm>
    <loanMaturityDate>07/2020</loanMaturityDate>
    <originalInterestRatePercentage>0.0459</originalInterestRatePercentage>
    <interestCalculationTypeCode>1</interestCalculationTypeCode>
    <originalInterestRateTypeCode>1</originalInterestRateTypeCode>
    <originalFirstPaymentDate>08/2014</originalFirstPaymentDate>
    <underwritingIndicator>true</underwritingIndicator>
    <gracePeriodNumber>1</gracePeriodNumber>
    <paymentTypeCode>2</paymentTypeCode>
    <subvented>0</subvented>
    <vehicleManufacturerName>GMC</vehicleManufacturerName>
    <vehicleModelName>Sierra                        </vehicleModelName>
    <vehicleNewUsedCode>1</vehicleNewUsedCode>
    <vehicleModelYear>2014</vehicleModelYear>
    <vehicleTypeCode>2</vehicleTypeCode>
    <vehicleValueAmount>31893.00</vehicleValueAmount>
    <vehicleValueSourceCode>1</vehicleValueSourceCode>
    <obligorCreditScoreType>Consumer Bureau</obligorCreditScoreType>
    <obligorCreditScore>736</obligorCreditScore>
    <obligorIncomeVerificationLevelCode>2</obligorIncomeVerificationLevelCode>
    <obligorEmploymentVerificationCode>2</obligorEmploymentVerificationCode>
    <coObligorIndicator>true</coObligorIndicator>
    <paymentToIncomePercentage>0.1067</paymentToIncomePercentage>
    <obligorGeographicLocation>PA</obligorGeographicLocation>
    <assetAddedIndicator>false</assetAddedIndicator>
    <remainingTermToMaturityNumber>20</remainingTermToMaturityNumber>
    <servicingAdvanceMethodCode>1</servicingAdvanceMethodCode>
    <reportingPeriodBeginningLoanBalanceAmount>8408.64</reportingPeriodBeginningLoanBalanceAmount>
    <nextReportingPeriodPaymentAmountDue>0.00</nextReportingPeriodPaymentAmountDue>
    <reportingPeriodInterestRatePercentage>0.0459</reportingPeriodInterestRatePercentage>
    <nextInterestRatePercentage>0.0459</nextInterestRatePercentage>
    <servicingFeePercentage>0.0100</servicingFeePercentage>
    <otherAssessedUncollectedServicerFeeAmount>0.00</otherAssessedUncollectedServicerFeeAmount>
    <scheduledInterestAmount>34.89</scheduledInterestAmount>
    <scheduledPrincipalAmount>409.53</scheduledPrincipalAmount>
    <otherPrincipalAdjustmentAmount>0.00</otherPrincipalAdjustmentAmount>
    <reportingPeriodActualEndBalanceAmount>7996.99</reportingPeriodActualEndBalanceAmount>
    <reportingPeriodScheduledPaymentAmount>444.42</reportingPeriodScheduledPaymentAmount>
    <totalActualAmountPaid>444.42</totalActualAmountPaid>
    <actualInterestCollectedAmount>32.77</actualInterestCollectedAmount>
    <actualPrincipalCollectedAmount>411.65</actualPrincipalCollectedAmount>
    <actualOtherCollectedAmount>0.00</actualOtherCollectedAmount>
    <interestPaidThroughDate>11-28-2018</interestPaidThroughDate>
    <currentDelinquencyStatus>0</currentDelinquencyStatus>
    <primaryLoanServicerName>Ally Bank</primaryLoanServicerName>
    <assetSubjectDemandIndicator>false</assetSubjectDemandIndicator>
    <repossessedIndicator>false</repossessedIndicator>
    <repossessedProceedsAmount>0.00</repossessedProceedsAmount>
  </assets>