<?xml version="1.0" encoding="Windows-1252"?>
<assets>
    <assetTypeNumber>Sponsor Assigned</assetTypeNumber>
    <assetNumber>21911299</assetNumber>
    <reportingPeriodBeginningDate>11-01-2018</reportingPeriodBeginningDate>
    <reportingPeriodEndingDate>11-30-2018</reportingPeriodEndingDate>
    <originatorName>Ally Bank</originatorName>
    <originationDate>12/2017</originationDate>
    <originalLoanAmount>17227.81</originalLoanAmount>
    <originalLoanTerm>73</originalLoanTerm>
    <loanMaturityDate>12/2023</loanMaturityDate>
    <originalInterestRatePercentage>0.0959</originalInterestRatePercentage>
    <interestCalculationTypeCode>1</interestCalculationTypeCode>
    <originalInterestRateTypeCode>1</originalInterestRateTypeCode>
    <originalFirstPaymentDate>01/2018</originalFirstPaymentDate>
    <underwritingIndicator>true</underwritingIndicator>
    <gracePeriodNumber>1</gracePeriodNumber>
    <paymentTypeCode>2</paymentTypeCode>
    <subvented>0</subvented>
    <vehicleManufacturerName>HYUNDAI</vehicleManufacturerName>
    <vehicleModelName>Sonata                        </vehicleModelName>
    <vehicleNewUsedCode>2</vehicleNewUsedCode>
    <vehicleModelYear>2015</vehicleModelYear>
    <vehicleTypeCode>1</vehicleTypeCode>
    <vehicleValueAmount>13425.00</vehicleValueAmount>
    <vehicleValueSourceCode>98</vehicleValueSourceCode>
    <obligorCreditScoreType>Consumer Bureau</obligorCreditScoreType>
    <obligorCreditScore>665</obligorCreditScore>
    <obligorIncomeVerificationLevelCode>2</obligorIncomeVerificationLevelCode>
    <obligorEmploymentVerificationCode>2</obligorEmploymentVerificationCode>
    <coObligorIndicator>false</coObligorIndicator>
    <paymentToIncomePercentage>0.1408</paymentToIncomePercentage>
    <obligorGeographicLocation>FL</obligorGeographicLocation>
    <assetAddedIndicator>false</assetAddedIndicator>
    <remainingTermToMaturityNumber>61</remainingTermToMaturityNumber>
    <servicingAdvanceMethodCode>1</servicingAdvanceMethodCode>
    <reportingPeriodBeginningLoanBalanceAmount>15380.31</reportingPeriodBeginningLoanBalanceAmount>
    <nextReportingPeriodPaymentAmountDue>252.89</nextReportingPeriodPaymentAmountDue>
    <reportingPeriodInterestRatePercentage>0.0959</reportingPeriodInterestRatePercentage>
    <nextInterestRatePercentage>0.0959</nextInterestRatePercentage>
    <servicingFeePercentage>0.0100</servicingFeePercentage>
    <otherAssessedUncollectedServicerFeeAmount>0.00</otherAssessedUncollectedServicerFeeAmount>
    <scheduledInterestAmount>125.70</scheduledInterestAmount>
    <scheduledPrincipalAmount>191.15</scheduledPrincipalAmount>
    <otherPrincipalAdjustmentAmount>0.00</otherPrincipalAdjustmentAmount>
    <reportingPeriodActualEndBalanceAmount>15153.05</reportingPeriodActualEndBalanceAmount>
    <reportingPeriodScheduledPaymentAmount>316.85</reportingPeriodScheduledPaymentAmount>
    <totalActualAmountPaid>380.81</totalActualAmountPaid>
    <actualInterestCollectedAmount>153.55</actualInterestCollectedAmount>
    <actualPrincipalCollectedAmount>227.26</actualPrincipalCollectedAmount>
    <actualOtherCollectedAmount>0.00</actualOtherCollectedAmount>
    <interestPaidThroughDate>11-26-2018</interestPaidThroughDate>
    <currentDelinquencyStatus>0</currentDelinquencyStatus>
    <primaryLoanServicerName>Ally Bank</primaryLoanServicerName>
    <assetSubjectDemandIndicator>false</assetSubjectDemandIndicator>
    <repossessedIndicator>false</repossessedIndicator>
    <repossessedProceedsAmount>0.00</repossessedProceedsAmount>
  </assets>