<?xml version="1.0" encoding="Windows-1252"?>
<assets>
    <assetTypeNumber>Sponsor Assigned</assetTypeNumber>
    <assetNumber>17954106</assetNumber>
    <reportingPeriodBeginningDate>11-01-2018</reportingPeriodBeginningDate>
    <reportingPeriodEndingDate>11-30-2018</reportingPeriodEndingDate>
    <originatorName>Ally Bank</originatorName>
    <originationDate>02/2015</originationDate>
    <originalLoanAmount>27538.97</originalLoanAmount>
    <originalLoanTerm>76</originalLoanTerm>
    <loanMaturityDate>03/2022</loanMaturityDate>
    <originalInterestRatePercentage>0.0870</originalInterestRatePercentage>
    <interestCalculationTypeCode>1</interestCalculationTypeCode>
    <originalInterestRateTypeCode>1</originalInterestRateTypeCode>
    <originalFirstPaymentDate>03/2015</originalFirstPaymentDate>
    <underwritingIndicator>true</underwritingIndicator>
    <gracePeriodNumber>1</gracePeriodNumber>
    <paymentTypeCode>2</paymentTypeCode>
    <subvented>2</subvented>
    <vehicleManufacturerName>CHRYSLER</vehicleManufacturerName>
    <vehicleModelName>200                           </vehicleModelName>
    <vehicleNewUsedCode>1</vehicleNewUsedCode>
    <vehicleModelYear>2015</vehicleModelYear>
    <vehicleTypeCode>1</vehicleTypeCode>
    <vehicleValueAmount>25871.00</vehicleValueAmount>
    <vehicleValueSourceCode>1</vehicleValueSourceCode>
    <obligorCreditScoreType>Consumer Bureau</obligorCreditScoreType>
    <obligorCreditScore>671</obligorCreditScore>
    <obligorIncomeVerificationLevelCode>2</obligorIncomeVerificationLevelCode>
    <obligorEmploymentVerificationCode>2</obligorEmploymentVerificationCode>
    <coObligorIndicator>false</coObligorIndicator>
    <paymentToIncomePercentage>0.0988</paymentToIncomePercentage>
    <obligorGeographicLocation>LA</obligorGeographicLocation>
    <assetAddedIndicator>false</assetAddedIndicator>
    <remainingTermToMaturityNumber>40</remainingTermToMaturityNumber>
    <servicingAdvanceMethodCode>1</servicingAdvanceMethodCode>
    <reportingPeriodBeginningLoanBalanceAmount>16811.97</reportingPeriodBeginningLoanBalanceAmount>
    <nextReportingPeriodPaymentAmountDue>958.06</nextReportingPeriodPaymentAmountDue>
    <reportingPeriodInterestRatePercentage>0.0870</reportingPeriodInterestRatePercentage>
    <nextInterestRatePercentage>0.0870</nextInterestRatePercentage>
    <servicingFeePercentage>0.0100</servicingFeePercentage>
    <otherAssessedUncollectedServicerFeeAmount>287.40</otherAssessedUncollectedServicerFeeAmount>
    <scheduledInterestAmount>97.85</scheduledInterestAmount>
    <scheduledPrincipalAmount>381.18</scheduledPrincipalAmount>
    <otherPrincipalAdjustmentAmount>-489.71</otherPrincipalAdjustmentAmount>
    <reportingPeriodActualEndBalanceAmount>16920.50</reportingPeriodActualEndBalanceAmount>
    <reportingPeriodScheduledPaymentAmount>479.03</reportingPeriodScheduledPaymentAmount>
    <totalActualAmountPaid>108.53</totalActualAmountPaid>
    <actualInterestCollectedAmount>108.53</actualInterestCollectedAmount>
    <actualPrincipalCollectedAmount>0.00</actualPrincipalCollectedAmount>
    <actualOtherCollectedAmount>0.00</actualOtherCollectedAmount>
    <interestPaidThroughDate>11-27-2018</interestPaidThroughDate>
    <currentDelinquencyStatus>4</currentDelinquencyStatus>
    <primaryLoanServicerName>Ally Bank</primaryLoanServicerName>
    <assetSubjectDemandIndicator>false</assetSubjectDemandIndicator>
    <repossessedIndicator>false</repossessedIndicator>
    <repossessedProceedsAmount>0.00</repossessedProceedsAmount>
  </assets>