<?xml version="1.0" encoding="Windows-1252"?>
<assets>
    <assetTypeNumber>Sponsor Assigned</assetTypeNumber>
    <assetNumber>21768518</assetNumber>
    <reportingPeriodBeginningDate>11-01-2018</reportingPeriodBeginningDate>
    <reportingPeriodEndingDate>11-30-2018</reportingPeriodEndingDate>
    <originatorName>Ally Bank</originatorName>
    <originationDate>11/2017</originationDate>
    <originalLoanAmount>42317.00</originalLoanAmount>
    <originalLoanTerm>73</originalLoanTerm>
    <loanMaturityDate>11/2023</loanMaturityDate>
    <originalInterestRatePercentage>0.0299</originalInterestRatePercentage>
    <interestCalculationTypeCode>1</interestCalculationTypeCode>
    <originalInterestRateTypeCode>1</originalInterestRateTypeCode>
    <originalFirstPaymentDate>12/2017</originalFirstPaymentDate>
    <underwritingIndicator>true</underwritingIndicator>
    <gracePeriodNumber>1</gracePeriodNumber>
    <paymentTypeCode>2</paymentTypeCode>
    <subvented>2</subvented>
    <vehicleManufacturerName>FORD</vehicleManufacturerName>
    <vehicleModelName>F-350                         </vehicleModelName>
    <vehicleNewUsedCode>1</vehicleNewUsedCode>
    <vehicleModelYear>2017</vehicleModelYear>
    <vehicleTypeCode>2</vehicleTypeCode>
    <vehicleValueAmount>67011.00</vehicleValueAmount>
    <vehicleValueSourceCode>1</vehicleValueSourceCode>
    <obligorCreditScoreType>Consumer Bureau</obligorCreditScoreType>
    <obligorCreditScore>802</obligorCreditScore>
    <obligorIncomeVerificationLevelCode>2</obligorIncomeVerificationLevelCode>
    <obligorEmploymentVerificationCode>2</obligorEmploymentVerificationCode>
    <coObligorIndicator>false</coObligorIndicator>
    <paymentToIncomePercentage>0.0423</paymentToIncomePercentage>
    <obligorGeographicLocation>CO</obligorGeographicLocation>
    <assetAddedIndicator>false</assetAddedIndicator>
    <remainingTermToMaturityNumber>60</remainingTermToMaturityNumber>
    <servicingAdvanceMethodCode>1</servicingAdvanceMethodCode>
    <reportingPeriodBeginningLoanBalanceAmount>36357.30</reportingPeriodBeginningLoanBalanceAmount>
    <nextReportingPeriodPaymentAmountDue>643.55</nextReportingPeriodPaymentAmountDue>
    <reportingPeriodInterestRatePercentage>0.0299</reportingPeriodInterestRatePercentage>
    <nextInterestRatePercentage>0.0299</nextInterestRatePercentage>
    <servicingFeePercentage>0.0100</servicingFeePercentage>
    <otherAssessedUncollectedServicerFeeAmount>0.00</otherAssessedUncollectedServicerFeeAmount>
    <scheduledInterestAmount>92.36</scheduledInterestAmount>
    <scheduledPrincipalAmount>551.19</scheduledPrincipalAmount>
    <otherPrincipalAdjustmentAmount>0.00</otherPrincipalAdjustmentAmount>
    <reportingPeriodActualEndBalanceAmount>35803.09</reportingPeriodActualEndBalanceAmount>
    <reportingPeriodScheduledPaymentAmount>643.55</reportingPeriodScheduledPaymentAmount>
    <totalActualAmountPaid>643.55</totalActualAmountPaid>
    <actualInterestCollectedAmount>89.34</actualInterestCollectedAmount>
    <actualPrincipalCollectedAmount>554.21</actualPrincipalCollectedAmount>
    <actualOtherCollectedAmount>0.00</actualOtherCollectedAmount>
    <interestPaidThroughDate>11-21-2018</interestPaidThroughDate>
    <currentDelinquencyStatus>0</currentDelinquencyStatus>
    <primaryLoanServicerName>Ally Bank</primaryLoanServicerName>
    <assetSubjectDemandIndicator>false</assetSubjectDemandIndicator>
    <repossessedIndicator>false</repossessedIndicator>
    <repossessedProceedsAmount>0.00</repossessedProceedsAmount>
  </assets>