<?xml version="1.0" encoding="Windows-1252"?>
<assets>
    <assetTypeNumber>Sponsor Assigned</assetTypeNumber>
    <assetNumber>22164299</assetNumber>
    <reportingPeriodBeginningDate>11-01-2018</reportingPeriodBeginningDate>
    <reportingPeriodEndingDate>11-30-2018</reportingPeriodEndingDate>
    <originatorName>Ally Bank</originatorName>
    <originationDate>02/2018</originationDate>
    <originalLoanAmount>5014.06</originalLoanAmount>
    <originalLoanTerm>49</originalLoanTerm>
    <loanMaturityDate>02/2022</loanMaturityDate>
    <originalInterestRatePercentage>0.0944</originalInterestRatePercentage>
    <interestCalculationTypeCode>1</interestCalculationTypeCode>
    <originalInterestRateTypeCode>1</originalInterestRateTypeCode>
    <originalFirstPaymentDate>03/2018</originalFirstPaymentDate>
    <underwritingIndicator>true</underwritingIndicator>
    <gracePeriodNumber>1</gracePeriodNumber>
    <paymentTypeCode>2</paymentTypeCode>
    <subvented>0</subvented>
    <vehicleManufacturerName>JEEP</vehicleManufacturerName>
    <vehicleModelName>Grand Cherokee                </vehicleModelName>
    <vehicleNewUsedCode>2</vehicleNewUsedCode>
    <vehicleModelYear>2007</vehicleModelYear>
    <vehicleTypeCode>3</vehicleTypeCode>
    <vehicleValueAmount>7400.00</vehicleValueAmount>
    <vehicleValueSourceCode>98</vehicleValueSourceCode>
    <obligorCreditScoreType>Consumer Bureau</obligorCreditScoreType>
    <obligorCreditScore>769</obligorCreditScore>
    <obligorIncomeVerificationLevelCode>2</obligorIncomeVerificationLevelCode>
    <obligorEmploymentVerificationCode>2</obligorEmploymentVerificationCode>
    <coObligorIndicator>false</coObligorIndicator>
    <paymentToIncomePercentage>0.0541</paymentToIncomePercentage>
    <obligorGeographicLocation>MN</obligorGeographicLocation>
    <assetAddedIndicator>false</assetAddedIndicator>
    <remainingTermToMaturityNumber>39</remainingTermToMaturityNumber>
    <servicingAdvanceMethodCode>1</servicingAdvanceMethodCode>
    <reportingPeriodBeginningLoanBalanceAmount>3187.89</reportingPeriodBeginningLoanBalanceAmount>
    <nextReportingPeriodPaymentAmountDue>0.00</nextReportingPeriodPaymentAmountDue>
    <reportingPeriodInterestRatePercentage>0.0944</reportingPeriodInterestRatePercentage>
    <nextInterestRatePercentage>0.0944</nextInterestRatePercentage>
    <servicingFeePercentage>0.0100</servicingFeePercentage>
    <otherAssessedUncollectedServicerFeeAmount>0.00</otherAssessedUncollectedServicerFeeAmount>
    <scheduledInterestAmount>34.64</scheduledInterestAmount>
    <scheduledPrincipalAmount>91.67</scheduledPrincipalAmount>
    <otherPrincipalAdjustmentAmount>0.00</otherPrincipalAdjustmentAmount>
    <reportingPeriodActualEndBalanceAmount>3087.13</reportingPeriodActualEndBalanceAmount>
    <reportingPeriodScheduledPaymentAmount>126.31</reportingPeriodScheduledPaymentAmount>
    <totalActualAmountPaid>126.31</totalActualAmountPaid>
    <actualInterestCollectedAmount>25.55</actualInterestCollectedAmount>
    <actualPrincipalCollectedAmount>100.76</actualPrincipalCollectedAmount>
    <actualOtherCollectedAmount>0.00</actualOtherCollectedAmount>
    <interestPaidThroughDate>11-26-2018</interestPaidThroughDate>
    <currentDelinquencyStatus>0</currentDelinquencyStatus>
    <primaryLoanServicerName>Ally Bank</primaryLoanServicerName>
    <assetSubjectDemandIndicator>false</assetSubjectDemandIndicator>
    <repossessedIndicator>false</repossessedIndicator>
    <repossessedProceedsAmount>0.00</repossessedProceedsAmount>
  </assets>